ml_workflow-0.8.4.data/data/workflow/template/cookiecutter.json
ml_workflow-0.8.4.data/data/workflow/template/{{cookiecutter.repository_name}}/.gitignore
ml_workflow-0.8.4.data/data/workflow/template/{{cookiecutter.repository_name}}/README.rst
ml_workflow-0.8.4.data/data/workflow/template/{{cookiecutter.repository_name}}/dev_requirements.txt
ml_workflow-0.8.4.data/data/workflow/template/{{cookiecutter.repository_name}}/guild.yml
ml_workflow-0.8.4.data/data/workflow/template/{{cookiecutter.repository_name}}/pytest.ini
ml_workflow-0.8.4.data/data/workflow/template/{{cookiecutter.repository_name}}/requirements.txt
ml_workflow-0.8.4.data/data/workflow/template/{{cookiecutter.repository_name}}/setup.cfg
ml_workflow-0.8.4.data/data/workflow/template/{{cookiecutter.repository_name}}/setup.py
ml_workflow-0.8.4.data/data/workflow/template/{{cookiecutter.repository_name}}/.github/workflows/publish.yml
ml_workflow-0.8.4.data/data/workflow/template/{{cookiecutter.repository_name}}/.github/workflows/test.yml
ml_workflow-0.8.4.data/data/workflow/template/{{cookiecutter.repository_name}}/operations/evaluate.py
ml_workflow-0.8.4.data/data/workflow/template/{{cookiecutter.repository_name}}/operations/prepare.py
ml_workflow-0.8.4.data/data/workflow/template/{{cookiecutter.repository_name}}/operations/search_lr.py
ml_workflow-0.8.4.data/data/workflow/template/{{cookiecutter.repository_name}}/operations/train.py
ml_workflow-0.8.4.data/data/workflow/template/{{cookiecutter.repository_name}}/{{cookiecutter.package_name}}/__init__.py
ml_workflow-0.8.4.data/data/workflow/template/{{cookiecutter.repository_name}}/{{cookiecutter.package_name}}/log_examples.py
ml_workflow-0.8.4.data/data/workflow/template/{{cookiecutter.repository_name}}/{{cookiecutter.package_name}}/metrics.py
ml_workflow-0.8.4.data/data/workflow/template/{{cookiecutter.repository_name}}/{{cookiecutter.package_name}}/train.py
ml_workflow-0.8.4.dist-info/AUTHORS
ml_workflow-0.8.4.dist-info/LICENSE
ml_workflow-0.8.4.dist-info/METADATA
ml_workflow-0.8.4.dist-info/WHEEL
ml_workflow-0.8.4.dist-info/entry_points.txt
ml_workflow-0.8.4.dist-info/pbr.json
ml_workflow-0.8.4.dist-info/top_level.txt
ml_workflow-0.8.4.dist-info/RECORD
